warfit_learn/__init__.py
warfit_learn/datasets/__init__.py
warfit_learn/datasets/loader.py
warfit_learn/datasets/data/iwpc.pkl
warfit_learn/estimators/__init__.py
warfit_learn/estimators/estimators.py
warfit_learn/evaluation/__init__.py
warfit_learn/evaluation/evaluation.py
warfit_learn/metrics/__init__.py
warfit_learn/metrics/scoring.py
warfit_learn/preprocessing/__init__.py
warfit_learn/preprocessing/preprocessor.py
warfit_learn-0.2.1.dist-info/LICENSE
warfit_learn-0.2.1.dist-info/METADATA
warfit_learn-0.2.1.dist-info/WHEEL
warfit_learn-0.2.1.dist-info/top_level.txt
warfit_learn-0.2.1.dist-info/RECORD
