Metadata-Version: 2.1
Name: warfit-learn
Version: 0.2.1
Summary: A toolkit for reproducible research in warfarin dose estimation
Home-page: https://github.com/gianlucatruda/warfit-learn
Author: Gianluca Truda
Author-email: gianlucatruda@gmail.com
License: UNKNOWN
Platform: UNKNOWN
Classifier: Programming Language :: Python :: 3
Classifier: Programming Language :: Python :: 3.6
Classifier: Programming Language :: Python :: 3.7
Classifier: License :: OSI Approved :: GNU General Public License v3 (GPLv3)
Classifier: Operating System :: OS Independent
Requires-Dist: numpy (>=1.14.5)
Requires-Dist: pandas (>=0.24.1)
Requires-Dist: scikit-learn (>=0.21.2)
Requires-Dist: scipy (>=1.1.0)
Requires-Dist: joblib (>=0.12.4)
Requires-Dist: tqdm (>=4.0)
Requires-Dist: tabulate (>=0.8.3)
